{"content":[{"id":"team","heading":{"short":"Meet Our Team","medium":"Get to Know the Faces Behind DOMMATI PRANAY","long":"Our Dedicated Team Working Towards a Common Goal at DOMMATI PRANAY"},"sentence":{"short":"Expertise and Passion Drive Our Team","medium":"Our Team Members Bring Diverse Skills and Dedication to Every Project"},"overline":{"short":"Team Members"},"button":{"short":"Meet the Team"},"secondary-button":{"short":"Learn More"}},{"id":"team-columns","columns":[{"title-medium":"Meet Our Team","sentence-short":"Dedicated professionals","sentence-medium":"Get to know the talented individuals behind our company"},{"title-medium":"Our Values","sentence-short":"Integrity and excellence","sentence-medium":"We uphold a commitment to integrity and strive for excellence in all we do"},{"title-medium":"Team Collaboration","sentence-short":"Strong teamwork","sentence-medium":"Collaboration is at the heart of our success, working together towards a common goal"},{"title-medium":"Meet the Experts","sentence-short":"Experts in their fields","sentence-medium":"Our team consists of experts with diverse skills and expertise"}]},{"id":"team-list","list":[{"list-item-short":"Team Members","list-item-long":"Our team consists of dedicated and skilled professionals from diverse backgrounds."},{"list-item-short":"Collaboration","list-item-long":"We believe in collaboration and synergy to deliver exceptional results for our clients."},{"list-item-short":"Expertise","list-item-long":"Each team member brings unique expertise and experience to the table, ensuring top-notch services."},{"list-item-short":"Passion","list-item-long":"Passion drives us to excel in the freelancer industry and provide unmatched services."},{"list-item-short":"Innovation","list-item-long":"We thrive on innovation and constantly adapt to meet the evolving needs of our clients."},{"list-item-short":"Dedication","list-item-long":"Our team is dedicated to upholding the highest standards of quality and professionalism."}]},{"id":"team-people","people":[{"name":"Sarah Johnson","position":"Lead Developer","sentence-short":"Experienced developer with a passion for creating innovative solutions."},{"name":"Michael Lee","position":"Marketing Specialist","sentence-short":"Strategist with a keen eye for detail and a creative approach to marketing."},{"name":"Emily Chen","position":"Graphic Designer","sentence-short":"Talented designer who brings ideas to life through captivating visuals."},{"name":"David Patel","position":"Content Creator","sentence-short":"Wordsmith crafting engaging content that resonates with audiences."},{"name":"Jessica Adams","position":"Social Media Manager","sentence-short":"Social media guru driving engagement and brand awareness."},{"name":"Alex Miller","position":"Customer Relations Specialist","sentence-short":"Dedicated professional committed to providing exceptional customer service."},{"name":"Olivia Taylor","position":"Finance Manager","sentence-short":"Analytical mind managing finances with precision and foresight."},{"name":"Daniel Clark","position":"IT Support Specialist","sentence-short":"Tech expert ensuring seamless operations and resolving issues efficiently."}]},{"id":"team-videos","videos":[{"title-short":"Meet the Team"},{"title-short":"Behind the Scenes"},{"title-short":"Day in the Life"},{"title-short":"Company Culture Insights"}]}]}